numpar/__init__.py
numpar-0.1.2.dist-info/LICENSE.md
numpar-0.1.2.dist-info/METADATA
numpar-0.1.2.dist-info/WHEEL
numpar-0.1.2.dist-info/top_level.txt
numpar-0.1.2.dist-info/RECORD
