Metadata-Version: 2.2
Name: numpar
Version: 0.1.2
Summary: A package for parsing number strings in various formats
Home-page: https://github.com/jkrup/numpar
Author: Just
Author-email: justin@bokuga.com
Classifier: Programming Language :: Python :: 3
Classifier: License :: OSI Approved :: MIT License
Classifier: Operating System :: OS Independent
Requires-Python: >=3.6
License-File: LICENSE.md
Dynamic: author
Dynamic: author-email
Dynamic: classifier
Dynamic: description
Dynamic: description-content-type
Dynamic: home-page
Dynamic: requires-python
Dynamic: summary
